{
  "techniques": [
    {
      "stages": "transparent",
      "parameters": {
        "mainTexture": {"type": "tex2d"},
        "color": {"type": "color4", "value": "0x00ff00ff"}
      },
      "passes": [
        {
          "blend": "add src_alpha one_minus_src_alpha",
          "blendAlpha": "add one one",
          "blendColor": "0xff00ff00",
          "cull": "back",
          "depth": "less false",
          "stencil": "always 0x0 0xff keep keep keep 0xff",
          "stencilBack": "always 0x0 0xff keep keep keep 0xff",
          "program": "simple"
        }
      ]
    }
  ]
}
